tdl_pybasic/__init__.py
tdl_pybasic/array.py
tdl_pybasic/draw_graph.py
tdl_pybasic/lfreq.py
tdl_pybasic/random.py
tdl_pybasic/assets/c6.wav
tdl_pybasic-0.1.12.dist-info/METADATA
tdl_pybasic-0.1.12.dist-info/WHEEL
tdl_pybasic-0.1.12.dist-info/top_level.txt
tdl_pybasic-0.1.12.dist-info/RECORD
