Metadata-Version: 2.1
Name: tdl-pybasic
Version: 0.1.12
Summary: A library for Toushin Digital University Python BASIC.
Home-page: UNKNOWN
Author: Atsushi Shibata
Author-email: shibata@m-info.co.jp
License: MIT
Platform: UNKNOWN
Classifier: License :: OSI Approved :: MIT License
Classifier: Programming Language :: Python :: 3.6
